numpyro_inferutils/__init__.py
numpyro_inferutils/fisher.py
numpyro_inferutils/logprob.py
numpyro_inferutils/optim.py
numpyro_inferutils/transforms.py
numpyro_inferutils-0.1.2.dist-info/METADATA
numpyro_inferutils-0.1.2.dist-info/WHEEL
numpyro_inferutils-0.1.2.dist-info/licenses/LICENSE
numpyro_inferutils-0.1.2.dist-info/RECORD
