Metadata-Version: 2.4
Name: numpyro-inferutils
Version: 0.1.2
Summary: Utility functions for extracting log-probabilities, parameter transforms, and Fisher information from NumPyro models.
Project-URL: Homepage, https://github.com/yourname/numpyro-inferutils
Project-URL: Source, https://github.com/yourname/numpyro-inferutils
Project-URL: Issues, https://github.com/yourname/numpyro-inferutils/issues
Author-email: Kento Masuda <kmasuda@ess.sci.osaka-u.ac.jp>
License: MIT
License-File: LICENSE
Requires-Python: >=3.10
Requires-Dist: jax>=0.4.30
Requires-Dist: jaxlib>=0.4.30
Requires-Dist: numpyro>=0.15.0
Provides-Extra: test
Requires-Dist: pytest; extra == 'test'
